{
  "username": "Nvg4991",
  "displayName": "Nick Belluscio",
  "overallStats": {
    "totalTournaments": 2,
    "totalPoints": 6,
    "totalMatches": 5,
    "matchRecord": "2-3-0",
    "matchWinPercentage": 0.4,
    "gameRecord": "6-7-0",
    "gameWinPercentage": 0.46153846153846156
  },
  "leagueStats": [
    {
      "leagueName": "Q3 2025",
      "events": 2,
      "points": 6,
      "matchRecord": "2-3-0",
      "matchWinPercentage": 0.4,
      "gameRecord": "6-7-0",
      "gameWinPercentage": 0.46153846153846156
    }
  ],
  "headToHead": [
    {
      "opponentUsername": "swbmtg",
      "opponentDisplayName": "swb 👋",
      "matchesPlayed": 1,
      "matchWins": 0,
      "matchLosses": 1,
      "matchDraws": 0,
      "matchWinPercentage": 0,
      "gameWins": 1,
      "gameLosses": 2,
      "gameDraws": 0,
      "gameWinPercentage": 0.3333333333333333,
      "lastFiveResults": [
        "L"
      ]
    },
    {
      "opponentUsername": "RichBucey",
      "opponentDisplayName": "RichBucey",
      "matchesPlayed": 1,
      "matchWins": 0,
      "matchLosses": 1,
      "matchDraws": 0,
      "matchWinPercentage": 0,
      "gameWins": 1,
      "gameLosses": 2,
      "gameDraws": 0,
      "gameWinPercentage": 0.3333333333333333,
      "lastFiveResults": [
        "L"
      ]
    },
    {
      "opponentUsername": "JUDDERMANG",
      "opponentDisplayName": "Chris Cruz",
      "matchesPlayed": 1,
      "matchWins": 1,
      "matchLosses": 0,
      "matchDraws": 0,
      "matchWinPercentage": 1,
      "gameWins": 2,
      "gameLosses": 0,
      "gameDraws": 0,
      "gameWinPercentage": 1,
      "lastFiveResults": [
        "W"
      ]
    },
    {
      "opponentUsername": "madmanpoet",
      "opponentDisplayName": "Michael Flores",
      "matchesPlayed": 1,
      "matchWins": 0,
      "matchLosses": 1,
      "matchDraws": 0,
      "matchWinPercentage": 0,
      "gameWins": 0,
      "gameLosses": 2,
      "gameDraws": 0,
      "gameWinPercentage": 0,
      "lastFiveResults": [
        "L"
      ]
    },
    {
      "opponentUsername": "Tencteri",
      "opponentDisplayName": "Tencteri",
      "matchesPlayed": 1,
      "matchWins": 1,
      "matchLosses": 0,
      "matchDraws": 0,
      "matchWinPercentage": 1,
      "gameWins": 2,
      "gameLosses": 1,
      "gameDraws": 0,
      "gameWinPercentage": 0.6666666666666666,
      "lastFiveResults": [
        "W"
      ]
    }
  ]
}