[
  {
    "Team": {
      "Players": [
        {
          "TeamId": 3782404,
          "ID": 3767740,
          "ScreenName": "N/A",
          "ProfileImageVersion": 2,
          "DisplayName": "Bill Ellis!!",
          "DisplayNameLastFirst": "Ellis!!, Bill",
          "Username": "FriendlyFerret",
          "LanguageDescription": "Auto (English)",
          "PronounsDescription": "He/Him"
        }
      ],
      "ID": 3782404,
      "Name": null,
      "StatusDescription": "Active",
      "IsActive": true
    },
    "DateCreated": "2026-01-09T03:21:21Z",
    "MatchingMethod": 0,
    "StandingsPublished": true,
    "FinalTiebreaker": 3782404,
    "OpponentGameWinPercentage": 0.4,
    "OpponentMatchWinPercentage": 0.5,
    "TeamGameWinPercentage": 1,
    "GameCount": 4,
    "GameDraws": 0,
    "GameLosses": 0,
    "GameWins": 4,
    "MatchCount": 2,
    "MatchDraws": 0,
    "MatchLosses": 0,
    "MatchWins": 2,
    "OpponentCount": 0,
    "PhaseSortOrder": 1,
    "Points": 6,
    "Rank": 1,
    "RoundNumber": 2,
    "ID": 63342455,
    "PhaseId": 396176,
    "RoundId": 1389668,
    "TeamId": 3782404,
    "TournamentId": 395699,
    "FormatId": "920ec64f-a02f-4176-a3d0-0c46eef003cb",
    "FormatName": "Premodern",
    "PhaseName": null,
    "MatchingMethodDescription": "Swiss",
    "Round": "Round 2",
    "Decklists": [],
    "GameRecord": "4-0-0",
    "MatchRecord": "2-0-0",
    "FormatDescription": "Premodern"
  },
  {
    "Team": {
      "Players": [
        {
          "TeamId": 3782438,
          "ID": 3767774,
          "ScreenName": "N/A",
          "ProfileImageVersion": 0,
          "DisplayName": "swb 👋",
          "DisplayNameLastFirst": "👋, swb",
          "Username": "swbmtg",
          "LanguageDescription": "Auto (English)",
          "PronounsDescription": "He/Him"
        }
      ],
      "ID": 3782438,
      "Name": null,
      "StatusDescription": "Active",
      "IsActive": true
    },
    "DateCreated": "2026-01-09T03:21:21Z",
    "MatchingMethod": 0,
    "StandingsPublished": true,
    "FinalTiebreaker": 3782438,
    "OpponentGameWinPercentage": 0.4,
    "OpponentMatchWinPercentage": 0.5,
    "TeamGameWinPercentage": 1,
    "GameCount": 4,
    "GameDraws": 0,
    "GameLosses": 0,
    "GameWins": 4,
    "MatchCount": 2,
    "MatchDraws": 0,
    "MatchLosses": 0,
    "MatchWins": 2,
    "OpponentCount": 0,
    "PhaseSortOrder": 1,
    "Points": 6,
    "Rank": 2,
    "RoundNumber": 2,
    "ID": 63342456,
    "PhaseId": 396176,
    "RoundId": 1389668,
    "TeamId": 3782438,
    "TournamentId": 395699,
    "FormatId": "920ec64f-a02f-4176-a3d0-0c46eef003cb",
    "FormatName": "Premodern",
    "PhaseName": null,
    "MatchingMethodDescription": "Swiss",
    "Round": "Round 2",
    "Decklists": [],
    "GameRecord": "4-0-0",
    "MatchRecord": "2-0-0",
    "FormatDescription": "Premodern"
  },
  {
    "Team": {
      "Players": [
        {
          "TeamId": 3782528,
          "ID": 3767864,
          "ScreenName": "N/A",
          "ProfileImageVersion": 0,
          "DisplayName": "ptscott",
          "DisplayNameLastFirst": "ptscott",
          "Username": "ptscott",
          "LanguageDescription": "Auto (English)",
          "PronounsDescription": null
        }
      ],
      "ID": 3782528,
      "Name": null,
      "StatusDescription": "Active",
      "IsActive": true
    },
    "DateCreated": "2026-01-09T03:21:21Z",
    "MatchingMethod": 0,
    "StandingsPublished": true,
    "FinalTiebreaker": 3782528,
    "OpponentGameWinPercentage": 0.5,
    "OpponentMatchWinPercentage": 0.5,
    "TeamGameWinPercentage": 0.8,
    "GameCount": 5,
    "GameDraws": 0,
    "GameLosses": 1,
    "GameWins": 4,
    "MatchCount": 2,
    "MatchDraws": 0,
    "MatchLosses": 0,
    "MatchWins": 2,
    "OpponentCount": 0,
    "PhaseSortOrder": 1,
    "Points": 6,
    "Rank": 3,
    "RoundNumber": 2,
    "ID": 63342457,
    "PhaseId": 396176,
    "RoundId": 1389668,
    "TeamId": 3782528,
    "TournamentId": 395699,
    "FormatId": "920ec64f-a02f-4176-a3d0-0c46eef003cb",
    "FormatName": "Premodern",
    "PhaseName": null,
    "MatchingMethodDescription": "Swiss",
    "Round": "Round 2",
    "Decklists": [],
    "GameRecord": "4-1-0",
    "MatchRecord": "2-0-0",
    "FormatDescription": "Premodern"
  },
  {
    "Team": {
      "Players": [
        {
          "TeamId": 3782482,
          "ID": 3767818,
          "ScreenName": "N/A",
          "ProfileImageVersion": 0,
          "DisplayName": "sjpenzer",
          "DisplayNameLastFirst": "sjpenzer",
          "Username": "sjpenzer",
          "LanguageDescription": "Auto (English)",
          "PronounsDescription": null
        }
      ],
      "ID": 3782482,
      "Name": null,
      "StatusDescription": "Active",
      "IsActive": true
    },
    "DateCreated": "2026-01-09T03:21:21Z",
    "MatchingMethod": 0,
    "StandingsPublished": true,
    "FinalTiebreaker": 3782482,
    "OpponentGameWinPercentage": 0.45,
    "OpponentMatchWinPercentage": 0.5,
    "TeamGameWinPercentage": 0.8,
    "GameCount": 5,
    "GameDraws": 0,
    "GameLosses": 1,
    "GameWins": 4,
    "MatchCount": 2,
    "MatchDraws": 0,
    "MatchLosses": 0,
    "MatchWins": 2,
    "OpponentCount": 0,
    "PhaseSortOrder": 1,
    "Points": 6,
    "Rank": 4,
    "RoundNumber": 2,
    "ID": 63342458,
    "PhaseId": 396176,
    "RoundId": 1389668,
    "TeamId": 3782482,
    "TournamentId": 395699,
    "FormatId": "920ec64f-a02f-4176-a3d0-0c46eef003cb",
    "FormatName": "Premodern",
    "PhaseName": null,
    "MatchingMethodDescription": "Swiss",
    "Round": "Round 2",
    "Decklists": [],
    "GameRecord": "4-1-0",
    "MatchRecord": "2-0-0",
    "FormatDescription": "Premodern"
  },
  {
    "Team": {
      "Players": [
        {
          "TeamId": 3782505,
          "ID": 3767841,
          "ScreenName": "N/A",
          "ProfileImageVersion": 0,
          "DisplayName": "Yosef Harari",
          "DisplayNameLastFirst": "Harari, Yosef",
          "Username": "itsCama",
          "LanguageDescription": "Auto (English)",
          "PronounsDescription": null
        }
      ],
      "ID": 3782505,
      "Name": null,
      "StatusDescription": "Active",
      "IsActive": true
    },
    "DateCreated": "2026-01-09T03:21:21Z",
    "MatchingMethod": 0,
    "StandingsPublished": true,
    "FinalTiebreaker": 3782505,
    "OpponentGameWinPercentage": 0.4166667,
    "OpponentMatchWinPercentage": 0.4166667,
    "TeamGameWinPercentage": 0.8,
    "GameCount": 5,
    "GameDraws": 0,
    "GameLosses": 1,
    "GameWins": 4,
    "MatchCount": 2,
    "MatchDraws": 0,
    "MatchLosses": 0,
    "MatchWins": 2,
    "OpponentCount": 0,
    "PhaseSortOrder": 1,
    "Points": 6,
    "Rank": 5,
    "RoundNumber": 2,
    "ID": 63342459,
    "PhaseId": 396176,
    "RoundId": 1389668,
    "TeamId": 3782505,
    "TournamentId": 395699,
    "FormatId": "920ec64f-a02f-4176-a3d0-0c46eef003cb",
    "FormatName": "Premodern",
    "PhaseName": null,
    "MatchingMethodDescription": "Swiss",
    "Round": "Round 2",
    "Decklists": [],
    "GameRecord": "4-1-0",
    "MatchRecord": "2-0-0",
    "FormatDescription": "Premodern"
  },
  {
    "Team": {
      "Players": [
        {
          "TeamId": 3782501,
          "ID": 3767837,
          "ScreenName": "N/A",
          "ProfileImageVersion": 0,
          "DisplayName": "Matt_W",
          "DisplayNameLastFirst": "Matt_W",
          "Username": "Matt_W",
          "LanguageDescription": "Auto (English)",
          "PronounsDescription": "He/Him"
        }
      ],
      "ID": 3782501,
      "Name": null,
      "StatusDescription": "Active",
      "IsActive": true
    },
    "DateCreated": "2026-01-09T03:21:21Z",
    "MatchingMethod": 0,
    "StandingsPublished": true,
    "FinalTiebreaker": 3782501,
    "OpponentGameWinPercentage": 0.575,
    "OpponentMatchWinPercentage": 0.5833333,
    "TeamGameWinPercentage": 0.75,
    "GameCount": 4,
    "GameDraws": 0,
    "GameLosses": 1,
    "GameWins": 3,
    "MatchCount": 2,
    "MatchDraws": 1,
    "MatchLosses": 0,
    "MatchWins": 1,
    "OpponentCount": 0,
    "PhaseSortOrder": 1,
    "Points": 4,
    "Rank": 6,
    "RoundNumber": 2,
    "ID": 63342460,
    "PhaseId": 396176,
    "RoundId": 1389668,
    "TeamId": 3782501,
    "TournamentId": 395699,
    "FormatId": "920ec64f-a02f-4176-a3d0-0c46eef003cb",
    "FormatName": "Premodern",
    "PhaseName": null,
    "MatchingMethodDescription": "Swiss",
    "Round": "Round 2",
    "Decklists": [],
    "GameRecord": "3-1-0",
    "MatchRecord": "1-0-1",
    "FormatDescription": "Premodern"
  },
  {
    "Team": {
      "Players": [
        {
          "TeamId": 3782494,
          "ID": 3767830,
          "ScreenName": "N/A",
          "ProfileImageVersion": 0,
          "DisplayName": "justintomczyk",
          "DisplayNameLastFirst": "justintomczyk",
          "Username": "justintomczyk",
          "LanguageDescription": "Auto (English)",
          "PronounsDescription": null
        }
      ],
      "ID": 3782494,
      "Name": null,
      "StatusDescription": "Active",
      "IsActive": true
    },
    "DateCreated": "2026-01-09T03:21:21Z",
    "MatchingMethod": 0,
    "StandingsPublished": true,
    "FinalTiebreaker": 3782494,
    "OpponentGameWinPercentage": 0.5416667,
    "OpponentMatchWinPercentage": 0.5,
    "TeamGameWinPercentage": 0.75,
    "GameCount": 4,
    "GameDraws": 0,
    "GameLosses": 1,
    "GameWins": 3,
    "MatchCount": 2,
    "MatchDraws": 1,
    "MatchLosses": 0,
    "MatchWins": 1,
    "OpponentCount": 0,
    "PhaseSortOrder": 1,
    "Points": 4,
    "Rank": 7,
    "RoundNumber": 2,
    "ID": 63342461,
    "PhaseId": 396176,
    "RoundId": 1389668,
    "TeamId": 3782494,
    "TournamentId": 395699,
    "FormatId": "920ec64f-a02f-4176-a3d0-0c46eef003cb",
    "FormatName": "Premodern",
    "PhaseName": null,
    "MatchingMethodDescription": "Swiss",
    "Round": "Round 2",
    "Decklists": [],
    "GameRecord": "3-1-0",
    "MatchRecord": "1-0-1",
    "FormatDescription": "Premodern"
  },
  {
    "Team": {
      "Players": [
        {
          "TeamId": 3782546,
          "ID": 3767882,
          "ScreenName": "N/A",
          "ProfileImageVersion": 0,
          "DisplayName": "BryanGulotta",
          "DisplayNameLastFirst": "BryanGulotta",
          "Username": "BryanGulotta",
          "LanguageDescription": "English (English)",
          "PronounsDescription": "He/Him"
        }
      ],
      "ID": 3782546,
      "Name": null,
      "StatusDescription": "Active",
      "IsActive": true
    },
    "DateCreated": "2026-01-09T03:21:21Z",
    "MatchingMethod": 0,
    "StandingsPublished": true,
    "FinalTiebreaker": 3782546,
    "OpponentGameWinPercentage": 0.65,
    "OpponentMatchWinPercentage": 0.75,
    "TeamGameWinPercentage": 0.5,
    "GameCount": 6,
    "GameDraws": 0,
    "GameLosses": 3,
    "GameWins": 3,
    "MatchCount": 2,
    "MatchDraws": 0,
    "MatchLosses": 1,
    "MatchWins": 1,
    "OpponentCount": 0,
    "PhaseSortOrder": 1,
    "Points": 3,
    "Rank": 8,
    "RoundNumber": 2,
    "ID": 63342462,
    "PhaseId": 396176,
    "RoundId": 1389668,
    "TeamId": 3782546,
    "TournamentId": 395699,
    "FormatId": "920ec64f-a02f-4176-a3d0-0c46eef003cb",
    "FormatName": "Premodern",
    "PhaseName": null,
    "MatchingMethodDescription": "Swiss",
    "Round": "Round 2",
    "Decklists": [],
    "GameRecord": "3-3-0",
    "MatchRecord": "1-1-0",
    "FormatDescription": "Premodern"
  },
  {
    "Team": {
      "Players": [
        {
          "TeamId": 3782513,
          "ID": 3767849,
          "ScreenName": "N/A",
          "ProfileImageVersion": 0,
          "DisplayName": "alexdeutch",
          "DisplayNameLastFirst": "alexdeutch",
          "Username": "alexdeutch",
          "LanguageDescription": "Auto (English)",
          "PronounsDescription": null
        }
      ],
      "ID": 3782513,
      "Name": null,
      "StatusDescription": "Active",
      "IsActive": true
    },
    "DateCreated": "2026-01-09T03:21:21Z",
    "MatchingMethod": 0,
    "StandingsPublished": true,
    "FinalTiebreaker": 3782513,
    "OpponentGameWinPercentage": 0.5666667,
    "OpponentMatchWinPercentage": 0.6666667,
    "TeamGameWinPercentage": 0.6,
    "GameCount": 5,
    "GameDraws": 0,
    "GameLosses": 2,
    "GameWins": 3,
    "MatchCount": 2,
    "MatchDraws": 0,
    "MatchLosses": 1,
    "MatchWins": 1,
    "OpponentCount": 0,
    "PhaseSortOrder": 1,
    "Points": 3,
    "Rank": 9,
    "RoundNumber": 2,
    "ID": 63342463,
    "PhaseId": 396176,
    "RoundId": 1389668,
    "TeamId": 3782513,
    "TournamentId": 395699,
    "FormatId": "920ec64f-a02f-4176-a3d0-0c46eef003cb",
    "FormatName": "Premodern",
    "PhaseName": null,
    "MatchingMethodDescription": "Swiss",
    "Round": "Round 2",
    "Decklists": [],
    "GameRecord": "3-2-0",
    "MatchRecord": "1-1-0",
    "FormatDescription": "Premodern"
  },
  {
    "Team": {
      "Players": [
        {
          "TeamId": 3782408,
          "ID": 3767744,
          "ScreenName": "N/A",
          "ProfileImageVersion": 0,
          "DisplayName": "RichBucey",
          "DisplayNameLastFirst": "RichBucey",
          "Username": "RichBucey",
          "LanguageDescription": "Auto (English)",
          "PronounsDescription": null
        }
      ],
      "ID": 3782408,
      "Name": null,
      "StatusDescription": "Active",
      "IsActive": true
    },
    "DateCreated": "2026-01-09T03:21:21Z",
    "MatchingMethod": 0,
    "StandingsPublished": true,
    "FinalTiebreaker": 3782408,
    "OpponentGameWinPercentage": 0.5666667,
    "OpponentMatchWinPercentage": 0.6666667,
    "TeamGameWinPercentage": 0.5,
    "GameCount": 6,
    "GameDraws": 0,
    "GameLosses": 3,
    "GameWins": 3,
    "MatchCount": 2,
    "MatchDraws": 0,
    "MatchLosses": 1,
    "MatchWins": 1,
    "OpponentCount": 0,
    "PhaseSortOrder": 1,
    "Points": 3,
    "Rank": 10,
    "RoundNumber": 2,
    "ID": 63342464,
    "PhaseId": 396176,
    "RoundId": 1389668,
    "TeamId": 3782408,
    "TournamentId": 395699,
    "FormatId": "920ec64f-a02f-4176-a3d0-0c46eef003cb",
    "FormatName": "Premodern",
    "PhaseName": null,
    "MatchingMethodDescription": "Swiss",
    "Round": "Round 2",
    "Decklists": [],
    "GameRecord": "3-3-0",
    "MatchRecord": "1-1-0",
    "FormatDescription": "Premodern"
  },
  {
    "Team": {
      "Players": [
        {
          "TeamId": 3782414,
          "ID": 3767750,
          "ScreenName": "N/A",
          "ProfileImageVersion": 0,
          "DisplayName": "Shawn Stroke",
          "DisplayNameLastFirst": "Stroke, Shawn",
          "Username": "sHaDes27",
          "LanguageDescription": "Auto (English)",
          "PronounsDescription": null
        }
      ],
      "ID": 3782414,
      "Name": null,
      "StatusDescription": "Active",
      "IsActive": true
    },
    "DateCreated": "2026-01-09T03:21:21Z",
    "MatchingMethod": 0,
    "StandingsPublished": true,
    "FinalTiebreaker": 3782414,
    "OpponentGameWinPercentage": 0.6666667,
    "OpponentMatchWinPercentage": 0.6666667,
    "TeamGameWinPercentage": 0.4,
    "GameCount": 5,
    "GameDraws": 0,
    "GameLosses": 3,
    "GameWins": 2,
    "MatchCount": 2,
    "MatchDraws": 0,
    "MatchLosses": 1,
    "MatchWins": 1,
    "OpponentCount": 0,
    "PhaseSortOrder": 1,
    "Points": 3,
    "Rank": 11,
    "RoundNumber": 2,
    "ID": 63342465,
    "PhaseId": 396176,
    "RoundId": 1389668,
    "TeamId": 3782414,
    "TournamentId": 395699,
    "FormatId": "920ec64f-a02f-4176-a3d0-0c46eef003cb",
    "FormatName": "Premodern",
    "PhaseName": null,
    "MatchingMethodDescription": "Swiss",
    "Round": "Round 2",
    "Decklists": [],
    "GameRecord": "2-3-0",
    "MatchRecord": "1-1-0",
    "FormatDescription": "Premodern"
  },
  {
    "Team": {
      "Players": [
        {
          "TeamId": 3782417,
          "ID": 3767753,
          "ScreenName": "N/A",
          "ProfileImageVersion": 0,
          "DisplayName": "Matthew Melachrinos",
          "DisplayNameLastFirst": "Melachrinos, Matthew",
          "Username": "Mattmelach",
          "LanguageDescription": "Auto (English)",
          "PronounsDescription": "He/Him"
        }
      ],
      "ID": 3782417,
      "Name": null,
      "StatusDescription": "Active",
      "IsActive": true
    },
    "DateCreated": "2026-01-09T03:21:21Z",
    "MatchingMethod": 0,
    "StandingsPublished": true,
    "FinalTiebreaker": 3782417,
    "OpponentGameWinPercentage": 0.6666667,
    "OpponentMatchWinPercentage": 0.6666667,
    "TeamGameWinPercentage": 0.4,
    "GameCount": 5,
    "GameDraws": 0,
    "GameLosses": 3,
    "GameWins": 2,
    "MatchCount": 2,
    "MatchDraws": 0,
    "MatchLosses": 1,
    "MatchWins": 1,
    "OpponentCount": 0,
    "PhaseSortOrder": 1,
    "Points": 3,
    "Rank": 12,
    "RoundNumber": 2,
    "ID": 63342466,
    "PhaseId": 396176,
    "RoundId": 1389668,
    "TeamId": 3782417,
    "TournamentId": 395699,
    "FormatId": "920ec64f-a02f-4176-a3d0-0c46eef003cb",
    "FormatName": "Premodern",
    "PhaseName": null,
    "MatchingMethodDescription": "Swiss",
    "Round": "Round 2",
    "Decklists": [],
    "GameRecord": "2-3-0",
    "MatchRecord": "1-1-0",
    "FormatDescription": "Premodern"
  },
  {
    "Team": {
      "Players": [
        {
          "TeamId": 3782452,
          "ID": 3767788,
          "ScreenName": "N/A",
          "ProfileImageVersion": 0,
          "DisplayName": "Jeremy Siegel",
          "DisplayNameLastFirst": "Siegel, Jeremy",
          "Username": "remixmtg",
          "LanguageDescription": "Auto (English)",
          "PronounsDescription": null
        }
      ],
      "ID": 3782452,
      "Name": null,
      "StatusDescription": "Active",
      "IsActive": true
    },
    "DateCreated": "2026-01-09T03:21:21Z",
    "MatchingMethod": 0,
    "StandingsPublished": true,
    "FinalTiebreaker": 3782452,
    "OpponentGameWinPercentage": 0.6666667,
    "OpponentMatchWinPercentage": 0.6666667,
    "TeamGameWinPercentage": 0.4,
    "GameCount": 5,
    "GameDraws": 0,
    "GameLosses": 3,
    "GameWins": 2,
    "MatchCount": 2,
    "MatchDraws": 0,
    "MatchLosses": 1,
    "MatchWins": 1,
    "OpponentCount": 0,
    "PhaseSortOrder": 1,
    "Points": 3,
    "Rank": 13,
    "RoundNumber": 2,
    "ID": 63342467,
    "PhaseId": 396176,
    "RoundId": 1389668,
    "TeamId": 3782452,
    "TournamentId": 395699,
    "FormatId": "920ec64f-a02f-4176-a3d0-0c46eef003cb",
    "FormatName": "Premodern",
    "PhaseName": null,
    "MatchingMethodDescription": "Swiss",
    "Round": "Round 2",
    "Decklists": [],
    "GameRecord": "2-3-0",
    "MatchRecord": "1-1-0",
    "FormatDescription": "Premodern"
  },
  {
    "Team": {
      "Players": [
        {
          "TeamId": 3782511,
          "ID": 3767847,
          "ScreenName": "N/A",
          "ProfileImageVersion": 0,
          "DisplayName": "Sean Fitzpatrick",
          "DisplayNameLastFirst": "Fitzpatrick, Sean",
          "Username": "SeaF9",
          "LanguageDescription": "Auto (English)",
          "PronounsDescription": null
        }
      ],
      "ID": 3782511,
      "Name": null,
      "StatusDescription": "Active",
      "IsActive": true
    },
    "DateCreated": "2026-01-09T03:21:21Z",
    "MatchingMethod": 0,
    "StandingsPublished": true,
    "FinalTiebreaker": 3782511,
    "OpponentGameWinPercentage": 0.6666667,
    "OpponentMatchWinPercentage": 0.6666667,
    "TeamGameWinPercentage": 0.4,
    "GameCount": 5,
    "GameDraws": 0,
    "GameLosses": 3,
    "GameWins": 2,
    "MatchCount": 2,
    "MatchDraws": 0,
    "MatchLosses": 1,
    "MatchWins": 1,
    "OpponentCount": 0,
    "PhaseSortOrder": 1,
    "Points": 3,
    "Rank": 14,
    "RoundNumber": 2,
    "ID": 63342468,
    "PhaseId": 396176,
    "RoundId": 1389668,
    "TeamId": 3782511,
    "TournamentId": 395699,
    "FormatId": "920ec64f-a02f-4176-a3d0-0c46eef003cb",
    "FormatName": "Premodern",
    "PhaseName": null,
    "MatchingMethodDescription": "Swiss",
    "Round": "Round 2",
    "Decklists": [],
    "GameRecord": "2-3-0",
    "MatchRecord": "1-1-0",
    "FormatDescription": "Premodern"
  },
  {
    "Team": {
      "Players": [
        {
          "TeamId": 3782497,
          "ID": 3767833,
          "ScreenName": "N/A",
          "ProfileImageVersion": 0,
          "DisplayName": "Taylorhol",
          "DisplayNameLastFirst": "Taylorhol",
          "Username": "Taylorhol",
          "LanguageDescription": "Auto (English)",
          "PronounsDescription": "He/Him"
        }
      ],
      "ID": 3782497,
      "Name": null,
      "StatusDescription": "Active",
      "IsActive": true
    },
    "DateCreated": "2026-01-09T03:21:21Z",
    "MatchingMethod": 0,
    "StandingsPublished": true,
    "FinalTiebreaker": 3782497,
    "OpponentGameWinPercentage": 0.5666667,
    "OpponentMatchWinPercentage": 0.6666667,
    "TeamGameWinPercentage": 0.4,
    "GameCount": 5,
    "GameDraws": 0,
    "GameLosses": 3,
    "GameWins": 2,
    "MatchCount": 2,
    "MatchDraws": 0,
    "MatchLosses": 1,
    "MatchWins": 1,
    "OpponentCount": 0,
    "PhaseSortOrder": 1,
    "Points": 3,
    "Rank": 15,
    "RoundNumber": 2,
    "ID": 63342469,
    "PhaseId": 396176,
    "RoundId": 1389668,
    "TeamId": 3782497,
    "TournamentId": 395699,
    "FormatId": "920ec64f-a02f-4176-a3d0-0c46eef003cb",
    "FormatName": "Premodern",
    "PhaseName": null,
    "MatchingMethodDescription": "Swiss",
    "Round": "Round 2",
    "Decklists": [],
    "GameRecord": "2-3-0",
    "MatchRecord": "1-1-0",
    "FormatDescription": "Premodern"
  },
  {
    "Team": {
      "Players": [
        {
          "TeamId": 3782531,
          "ID": 3767867,
          "ScreenName": "N/A",
          "ProfileImageVersion": 0,
          "DisplayName": "peatsheepening",
          "DisplayNameLastFirst": "peatsheepening",
          "Username": "peatsheepening",
          "LanguageDescription": "Auto (English)",
          "PronounsDescription": null
        }
      ],
      "ID": 3782531,
      "Name": null,
      "StatusDescription": "Active",
      "IsActive": true
    },
    "DateCreated": "2026-01-09T03:21:21Z",
    "MatchingMethod": 0,
    "StandingsPublished": true,
    "FinalTiebreaker": 3782531,
    "OpponentGameWinPercentage": 0.5666667,
    "OpponentMatchWinPercentage": 0.6666667,
    "TeamGameWinPercentage": 0.4,
    "GameCount": 5,
    "GameDraws": 0,
    "GameLosses": 3,
    "GameWins": 2,
    "MatchCount": 2,
    "MatchDraws": 0,
    "MatchLosses": 1,
    "MatchWins": 1,
    "OpponentCount": 0,
    "PhaseSortOrder": 1,
    "Points": 3,
    "Rank": 16,
    "RoundNumber": 2,
    "ID": 63342470,
    "PhaseId": 396176,
    "RoundId": 1389668,
    "TeamId": 3782531,
    "TournamentId": 395699,
    "FormatId": "920ec64f-a02f-4176-a3d0-0c46eef003cb",
    "FormatName": "Premodern",
    "PhaseName": null,
    "MatchingMethodDescription": "Swiss",
    "Round": "Round 2",
    "Decklists": [],
    "GameRecord": "2-3-0",
    "MatchRecord": "1-1-0",
    "FormatDescription": "Premodern"
  },
  {
    "Team": {
      "Players": [
        {
          "TeamId": 3782413,
          "ID": 3767749,
          "ScreenName": "N/A",
          "ProfileImageVersion": 3,
          "DisplayName": "Chris Cruz",
          "DisplayNameLastFirst": "Cruz, Chris",
          "Username": "JUDDERMANG",
          "LanguageDescription": "English (English)",
          "PronounsDescription": "He/They"
        }
      ],
      "ID": 3782413,
      "Name": null,
      "StatusDescription": "Active",
      "IsActive": true
    },
    "DateCreated": "2026-01-09T03:21:21Z",
    "MatchingMethod": 0,
    "StandingsPublished": true,
    "FinalTiebreaker": 3782413,
    "OpponentGameWinPercentage": 0.5416667,
    "OpponentMatchWinPercentage": 0.5,
    "TeamGameWinPercentage": 0.4,
    "GameCount": 5,
    "GameDraws": 0,
    "GameLosses": 3,
    "GameWins": 2,
    "MatchCount": 2,
    "MatchDraws": 0,
    "MatchLosses": 1,
    "MatchWins": 1,
    "OpponentCount": 0,
    "PhaseSortOrder": 1,
    "Points": 3,
    "Rank": 17,
    "RoundNumber": 2,
    "ID": 63342471,
    "PhaseId": 396176,
    "RoundId": 1389668,
    "TeamId": 3782413,
    "TournamentId": 395699,
    "FormatId": "920ec64f-a02f-4176-a3d0-0c46eef003cb",
    "FormatName": "Premodern",
    "PhaseName": null,
    "MatchingMethodDescription": "Swiss",
    "Round": "Round 2",
    "Decklists": [],
    "GameRecord": "2-3-0",
    "MatchRecord": "1-1-0",
    "FormatDescription": "Premodern"
  },
  {
    "Team": {
      "Players": [
        {
          "TeamId": 3782506,
          "ID": 3767842,
          "ScreenName": "N/A",
          "ProfileImageVersion": 0,
          "DisplayName": "Alex Profaci",
          "DisplayNameLastFirst": "Profaci, Alex",
          "Username": "aprofaci",
          "LanguageDescription": "English (English)",
          "PronounsDescription": "He/Him"
        }
      ],
      "ID": 3782506,
      "Name": null,
      "StatusDescription": "Active",
      "IsActive": true
    },
    "DateCreated": "2026-01-09T03:21:21Z",
    "MatchingMethod": 0,
    "StandingsPublished": true,
    "FinalTiebreaker": 3782506,
    "OpponentGameWinPercentage": 0.4166667,
    "OpponentMatchWinPercentage": 0.4166667,
    "TeamGameWinPercentage": 0.5,
    "GameCount": 4,
    "GameDraws": 0,
    "GameLosses": 2,
    "GameWins": 2,
    "MatchCount": 2,
    "MatchDraws": 0,
    "MatchLosses": 1,
    "MatchWins": 1,
    "OpponentCount": 0,
    "PhaseSortOrder": 1,
    "Points": 3,
    "Rank": 18,
    "RoundNumber": 2,
    "ID": 63342472,
    "PhaseId": 396176,
    "RoundId": 1389668,
    "TeamId": 3782506,
    "TournamentId": 395699,
    "FormatId": "920ec64f-a02f-4176-a3d0-0c46eef003cb",
    "FormatName": "Premodern",
    "PhaseName": null,
    "MatchingMethodDescription": "Swiss",
    "Round": "Round 2",
    "Decklists": [],
    "GameRecord": "2-2-0",
    "MatchRecord": "1-1-0",
    "FormatDescription": "Premodern"
  },
  {
    "Team": {
      "Players": [
        {
          "TeamId": 3782500,
          "ID": 3767836,
          "ScreenName": "N/A",
          "ProfileImageVersion": 0,
          "DisplayName": "zjr",
          "DisplayNameLastFirst": "zjr",
          "Username": "zjr",
          "LanguageDescription": "Auto (English)",
          "PronounsDescription": null
        }
      ],
      "ID": 3782500,
      "Name": null,
      "StatusDescription": "Active",
      "IsActive": true
    },
    "DateCreated": "2026-01-09T03:21:21Z",
    "MatchingMethod": 0,
    "StandingsPublished": true,
    "FinalTiebreaker": 3782500,
    "OpponentGameWinPercentage": 0.6,
    "OpponentMatchWinPercentage": 0.75,
    "TeamGameWinPercentage": 0.3333333,
    "GameCount": 5,
    "GameDraws": 0,
    "GameLosses": 4,
    "GameWins": 1,
    "MatchCount": 2,
    "MatchDraws": 0,
    "MatchLosses": 2,
    "MatchWins": 0,
    "OpponentCount": 0,
    "PhaseSortOrder": 1,
    "Points": 0,
    "Rank": 19,
    "RoundNumber": 2,
    "ID": 63342473,
    "PhaseId": 396176,
    "RoundId": 1389668,
    "TeamId": 3782500,
    "TournamentId": 395699,
    "FormatId": "920ec64f-a02f-4176-a3d0-0c46eef003cb",
    "FormatName": "Premodern",
    "PhaseName": null,
    "MatchingMethodDescription": "Swiss",
    "Round": "Round 2",
    "Decklists": [],
    "GameRecord": "1-4-0",
    "MatchRecord": "0-2-0",
    "FormatDescription": "Premodern"
  },
  {
    "Team": {
      "Players": [
        {
          "TeamId": 3782435,
          "ID": 3767771,
          "ScreenName": "N/A",
          "ProfileImageVersion": 0,
          "DisplayName": "Michael Flores",
          "DisplayNameLastFirst": "Flores, Michael",
          "Username": "madmanpoet",
          "LanguageDescription": "Auto (English)",
          "PronounsDescription": "He/Him"
        }
      ],
      "ID": 3782435,
      "Name": null,
      "StatusDescription": "Active",
      "IsActive": true
    },
    "DateCreated": "2026-01-09T03:21:21Z",
    "MatchingMethod": 0,
    "StandingsPublished": true,
    "FinalTiebreaker": 3782435,
    "OpponentGameWinPercentage": 0.575,
    "OpponentMatchWinPercentage": 0.5833333,
    "TeamGameWinPercentage": 0.3333333,
    "GameCount": 5,
    "GameDraws": 0,
    "GameLosses": 4,
    "GameWins": 1,
    "MatchCount": 2,
    "MatchDraws": 0,
    "MatchLosses": 2,
    "MatchWins": 0,
    "OpponentCount": 0,
    "PhaseSortOrder": 1,
    "Points": 0,
    "Rank": 20,
    "RoundNumber": 2,
    "ID": 63342474,
    "PhaseId": 396176,
    "RoundId": 1389668,
    "TeamId": 3782435,
    "TournamentId": 395699,
    "FormatId": "920ec64f-a02f-4176-a3d0-0c46eef003cb",
    "FormatName": "Premodern",
    "PhaseName": null,
    "MatchingMethodDescription": "Swiss",
    "Round": "Round 2",
    "Decklists": [],
    "GameRecord": "1-4-0",
    "MatchRecord": "0-2-0",
    "FormatDescription": "Premodern"
  },
  {
    "Team": {
      "Players": [
        {
          "TeamId": 3782518,
          "ID": 3767854,
          "ScreenName": "N/A",
          "ProfileImageVersion": 0,
          "DisplayName": "mauriceg123",
          "DisplayNameLastFirst": "mauriceg123",
          "Username": "mauriceg123",
          "LanguageDescription": "Auto (English)",
          "PronounsDescription": null
        }
      ],
      "ID": 3782518,
      "Name": null,
      "StatusDescription": "Active",
      "IsActive": true
    },
    "DateCreated": "2026-01-09T03:21:21Z",
    "MatchingMethod": 0,
    "StandingsPublished": true,
    "FinalTiebreaker": 3782518,
    "OpponentGameWinPercentage": 0.55,
    "OpponentMatchWinPercentage": 0.5,
    "TeamGameWinPercentage": 0.3333333,
    "GameCount": 3,
    "GameDraws": 0,
    "GameLosses": 3,
    "GameWins": 0,
    "MatchCount": 2,
    "MatchDraws": 0,
    "MatchLosses": 2,
    "MatchWins": 0,
    "OpponentCount": 0,
    "PhaseSortOrder": 1,
    "Points": 0,
    "Rank": 21,
    "RoundNumber": 2,
    "ID": 63342475,
    "PhaseId": 396176,
    "RoundId": 1389668,
    "TeamId": 3782518,
    "TournamentId": 395699,
    "FormatId": "920ec64f-a02f-4176-a3d0-0c46eef003cb",
    "FormatName": "Premodern",
    "PhaseName": null,
    "MatchingMethodDescription": "Swiss",
    "Round": "Round 2",
    "Decklists": [],
    "GameRecord": "0-3-0",
    "MatchRecord": "0-2-0",
    "FormatDescription": "Premodern"
  },
  {
    "Team": {
      "Players": [
        {
          "TeamId": 3782428,
          "ID": 3767764,
          "ScreenName": "N/A",
          "ProfileImageVersion": 0,
          "DisplayName": "JohnnyDalz",
          "DisplayNameLastFirst": "JohnnyDalz",
          "Username": "JohnnyDalz",
          "LanguageDescription": "Auto (English)",
          "PronounsDescription": null
        }
      ],
      "ID": 3782428,
      "Name": null,
      "StatusDescription": "Active",
      "IsActive": true
    },
    "DateCreated": "2026-01-09T03:21:21Z",
    "MatchingMethod": 0,
    "StandingsPublished": true,
    "FinalTiebreaker": 3782428,
    "OpponentGameWinPercentage": 0.45,
    "OpponentMatchWinPercentage": 0.5,
    "TeamGameWinPercentage": 0.3333333,
    "GameCount": 6,
    "GameDraws": 0,
    "GameLosses": 4,
    "GameWins": 2,
    "MatchCount": 2,
    "MatchDraws": 0,
    "MatchLosses": 2,
    "MatchWins": 0,
    "OpponentCount": 0,
    "PhaseSortOrder": 1,
    "Points": 0,
    "Rank": 22,
    "RoundNumber": 2,
    "ID": 63342476,
    "PhaseId": 396176,
    "RoundId": 1389668,
    "TeamId": 3782428,
    "TournamentId": 395699,
    "FormatId": "920ec64f-a02f-4176-a3d0-0c46eef003cb",
    "FormatName": "Premodern",
    "PhaseName": null,
    "MatchingMethodDescription": "Swiss",
    "Round": "Round 2",
    "Decklists": [],
    "GameRecord": "2-4-0",
    "MatchRecord": "0-2-0",
    "FormatDescription": "Premodern"
  },
  {
    "Team": {
      "Players": [
        {
          "TeamId": 3782403,
          "ID": 3767739,
          "ScreenName": "N/A",
          "ProfileImageVersion": 0,
          "DisplayName": "AndrewLevine",
          "DisplayNameLastFirst": "AndrewLevine",
          "Username": "AndrewLevine",
          "LanguageDescription": "English (English)",
          "PronounsDescription": "He/Him"
        }
      ],
      "ID": 3782403,
      "Name": null,
      "StatusDescription": "Active",
      "IsActive": true
    },
    "DateCreated": "2026-01-09T03:21:21Z",
    "MatchingMethod": 0,
    "StandingsPublished": true,
    "FinalTiebreaker": 3782403,
    "OpponentGameWinPercentage": 0.4,
    "OpponentMatchWinPercentage": 0.5,
    "TeamGameWinPercentage": 0.3333333,
    "GameCount": 6,
    "GameDraws": 0,
    "GameLosses": 4,
    "GameWins": 2,
    "MatchCount": 2,
    "MatchDraws": 0,
    "MatchLosses": 2,
    "MatchWins": 0,
    "OpponentCount": 0,
    "PhaseSortOrder": 1,
    "Points": 0,
    "Rank": 23,
    "RoundNumber": 2,
    "ID": 63342477,
    "PhaseId": 396176,
    "RoundId": 1389668,
    "TeamId": 3782403,
    "TournamentId": 395699,
    "FormatId": "920ec64f-a02f-4176-a3d0-0c46eef003cb",
    "FormatName": "Premodern",
    "PhaseName": null,
    "MatchingMethodDescription": "Swiss",
    "Round": "Round 2",
    "Decklists": [],
    "GameRecord": "2-4-0",
    "MatchRecord": "0-2-0",
    "FormatDescription": "Premodern"
  },
  {
    "Team": {
      "Players": [
        {
          "TeamId": 3782495,
          "ID": 3767831,
          "ScreenName": "N/A",
          "ProfileImageVersion": 0,
          "DisplayName": "Tencteri",
          "DisplayNameLastFirst": "Tencteri",
          "Username": "Tencteri",
          "LanguageDescription": "Auto (English)",
          "PronounsDescription": null
        }
      ],
      "ID": 3782495,
      "Name": null,
      "StatusDescription": "Active",
      "IsActive": true
    },
    "DateCreated": "2026-01-09T03:21:21Z",
    "MatchingMethod": 0,
    "StandingsPublished": true,
    "FinalTiebreaker": 3782495,
    "OpponentGameWinPercentage": 0.4,
    "OpponentMatchWinPercentage": 0.5,
    "TeamGameWinPercentage": 0.3333333,
    "GameCount": 6,
    "GameDraws": 0,
    "GameLosses": 4,
    "GameWins": 2,
    "MatchCount": 2,
    "MatchDraws": 0,
    "MatchLosses": 2,
    "MatchWins": 0,
    "OpponentCount": 0,
    "PhaseSortOrder": 1,
    "Points": 0,
    "Rank": 24,
    "RoundNumber": 2,
    "ID": 63342478,
    "PhaseId": 396176,
    "RoundId": 1389668,
    "TeamId": 3782495,
    "TournamentId": 395699,
    "FormatId": "920ec64f-a02f-4176-a3d0-0c46eef003cb",
    "FormatName": "Premodern",
    "PhaseName": null,
    "MatchingMethodDescription": "Swiss",
    "Round": "Round 2",
    "Decklists": [],
    "GameRecord": "2-4-0",
    "MatchRecord": "0-2-0",
    "FormatDescription": "Premodern"
  }
]