[
  {
    "Competitors": [
      {
        "Team": {
          "Players": [
            {
              "TeamId": 3261876,
              "ID": 3247212,
              "ScreenName": "N/A",
              "ProfileImageVersion": 0,
              "DisplayName": "BryanGulotta",
              "DisplayNameLastFirst": "BryanGulotta",
              "Username": "BryanGulotta",
              "LanguageDescription": "English (English)",
              "PronounsDescription": "He/Him"
            }
          ],
          "ID": 3261876,
          "Name": null,
          "StatusDescription": "Active",
          "IsActive": true
        },
        "ID": 10877794,
        "CheckedIn": "2025-06-20T00:02:14Z",
        "ResultConfirmed": "2025-06-20T00:02:14Z",
        "SortOrder": 0,
        "GameByes": 2,
        "GameWins": null,
        "TeamId": 3261876,
        "GameWinsAndGameByes": 2,
        "Decklists": []
      }
    ],
    "ByeReason": 0,
    "LossReason": null,
    "RoundName": null,
    "DateCreated": "2025-06-20T00:02:14Z",
    "Type": 0,
    "FeatureMatch": false,
    "HasResult": true,
    "TimeExtended": false,
    "MatchesPublished": true,
    "RoundNumber": 2,
    "GameDraws": 0,
    "PodNumber": null,
    "PhaseSortOrder": 1,
    "SortOrder": null,
    "TableNumber": null,
    "TimeExtensionMinutes": null,
    "PhaseId": 328387,
    "RoundId": 1151673,
    "TournamentId": 328861,
    "FormatId": "920ec64f-a02f-4176-a3d0-0c46eef003cb",
    "Format": "Premodern",
    "Guid": "8d8c59a9-b1d4-41e1-9146-b30200009d2c",
    "TableLocation": null,
    "TableSection": null,
    "ByeReasonDescription": "Algorithm Assigned",
    "LossReasonDescription": null,
    "ResultString": "BryanGulotta was assigned a bye",
    "RoundDescription": "Round 2",
    "TableNumberDescription": null,
    "TypeDescription": "Best of Three",
    "FormatDescription": "Premodern",
    "AcknowledgedDecklists": false
  },
  {
    "Competitors": [
      {
        "Team": {
          "Players": [
            {
              "TeamId": 3261865,
              "ID": 3247201,
              "ScreenName": "N/A",
              "ProfileImageVersion": 0,
              "DisplayName": "Gregory Berlinrut",
              "DisplayNameLastFirst": "Berlinrut, Gregory",
              "Username": "gberlinrut",
              "LanguageDescription": "Auto (English)",
              "PronounsDescription": "He/Him"
            }
          ],
          "ID": 3261865,
          "Name": null,
          "StatusDescription": "Active",
          "IsActive": true
        },
        "ID": 10877795,
        "CheckedIn": null,
        "ResultConfirmed": "2025-06-20T00:35:14Z",
        "SortOrder": 0,
        "GameByes": 0,
        "GameWins": 2,
        "TeamId": 3261865,
        "GameWinsAndGameByes": 2,
        "Decklists": []
      },
      {
        "Team": {
          "Players": [
            {
              "TeamId": 3261781,
              "ID": 3247117,
              "ScreenName": "N/A",
              "ProfileImageVersion": 0,
              "DisplayName": "Tencteri",
              "DisplayNameLastFirst": "Tencteri",
              "Username": "Tencteri",
              "LanguageDescription": "Auto (English)",
              "PronounsDescription": null
            }
          ],
          "ID": 3261781,
          "Name": null,
          "StatusDescription": "Active",
          "IsActive": true
        },
        "ID": 10877796,
        "CheckedIn": null,
        "ResultConfirmed": null,
        "SortOrder": 1,
        "GameByes": 0,
        "GameWins": 0,
        "TeamId": 3261781,
        "GameWinsAndGameByes": 0,
        "Decklists": []
      }
    ],
    "ByeReason": null,
    "LossReason": null,
    "RoundName": null,
    "DateCreated": "2025-06-20T00:35:14Z",
    "Type": 0,
    "FeatureMatch": false,
    "HasResult": true,
    "TimeExtended": false,
    "MatchesPublished": true,
    "RoundNumber": 2,
    "GameDraws": 0,
    "PodNumber": null,
    "PhaseSortOrder": 1,
    "SortOrder": null,
    "TableNumber": 1,
    "TimeExtensionMinutes": null,
    "PhaseId": 328387,
    "RoundId": 1151673,
    "TournamentId": 328861,
    "FormatId": "920ec64f-a02f-4176-a3d0-0c46eef003cb",
    "Format": "Premodern",
    "Guid": "162280f8-382e-427f-b6fb-b30200009d2e",
    "TableLocation": null,
    "TableSection": null,
    "ByeReasonDescription": null,
    "LossReasonDescription": null,
    "ResultString": "Gregory Berlinrut won 2-0-0",
    "RoundDescription": "Round 2",
    "TableNumberDescription": "1",
    "TypeDescription": "Best of Three",
    "FormatDescription": "Premodern",
    "AcknowledgedDecklists": false
  },
  {
    "Competitors": [
      {
        "Team": {
          "Players": [
            {
              "TeamId": 3261910,
              "ID": 3247246,
              "ScreenName": "N/A",
              "ProfileImageVersion": 0,
              "DisplayName": "Michael Flores",
              "DisplayNameLastFirst": "Flores, Michael",
              "Username": "madmanpoet",
              "LanguageDescription": "Auto (English)",
              "PronounsDescription": "He/Him"
            }
          ],
          "ID": 3261910,
          "Name": null,
          "StatusDescription": "Active",
          "IsActive": true
        },
        "ID": 10877797,
        "CheckedIn": null,
        "ResultConfirmed": "2025-06-20T00:54:20Z",
        "SortOrder": 0,
        "GameByes": 0,
        "GameWins": 2,
        "TeamId": 3261910,
        "GameWinsAndGameByes": 2,
        "Decklists": []
      },
      {
        "Team": {
          "Players": [
            {
              "TeamId": 3261879,
              "ID": 3247215,
              "ScreenName": "N/A",
              "ProfileImageVersion": 0,
              "DisplayName": "DEL .",
              "DisplayNameLastFirst": "., DEL",
              "Username": "delofstrom",
              "LanguageDescription": "Auto (English)",
              "PronounsDescription": "He/Him"
            }
          ],
          "ID": 3261879,
          "Name": null,
          "StatusDescription": "Active",
          "IsActive": true
        },
        "ID": 10877798,
        "CheckedIn": null,
        "ResultConfirmed": null,
        "SortOrder": 1,
        "GameByes": 0,
        "GameWins": 1,
        "TeamId": 3261879,
        "GameWinsAndGameByes": 1,
        "Decklists": []
      }
    ],
    "ByeReason": null,
    "LossReason": null,
    "RoundName": null,
    "DateCreated": "2025-06-20T00:54:20Z",
    "Type": 0,
    "FeatureMatch": false,
    "HasResult": true,
    "TimeExtended": false,
    "MatchesPublished": true,
    "RoundNumber": 2,
    "GameDraws": 0,
    "PodNumber": null,
    "PhaseSortOrder": 1,
    "SortOrder": null,
    "TableNumber": 2,
    "TimeExtensionMinutes": null,
    "PhaseId": 328387,
    "RoundId": 1151673,
    "TournamentId": 328861,
    "FormatId": "920ec64f-a02f-4176-a3d0-0c46eef003cb",
    "Format": "Premodern",
    "Guid": "9c69e621-8a87-4076-97a5-b30200009d37",
    "TableLocation": null,
    "TableSection": null,
    "ByeReasonDescription": null,
    "LossReasonDescription": null,
    "ResultString": "Michael Flores won 2-1-0",
    "RoundDescription": "Round 2",
    "TableNumberDescription": "2",
    "TypeDescription": "Best of Three",
    "FormatDescription": "Premodern",
    "AcknowledgedDecklists": false
  },
  {
    "Competitors": [
      {
        "Team": {
          "Players": [
            {
              "TeamId": 3261929,
              "ID": 3247265,
              "ScreenName": "N/A",
              "ProfileImageVersion": 0,
              "DisplayName": "AndrewLevine",
              "DisplayNameLastFirst": "AndrewLevine",
              "Username": "AndrewLevine",
              "LanguageDescription": "English (English)",
              "PronounsDescription": "He/Him"
            }
          ],
          "ID": 3261929,
          "Name": null,
          "StatusDescription": "Active",
          "IsActive": true
        },
        "ID": 10877799,
        "CheckedIn": null,
        "ResultConfirmed": null,
        "SortOrder": 0,
        "GameByes": 0,
        "GameWins": 0,
        "TeamId": 3261929,
        "GameWinsAndGameByes": 0,
        "Decklists": []
      },
      {
        "Team": {
          "Players": [
            {
              "TeamId": 3261782,
              "ID": 3247118,
              "ScreenName": "N/A",
              "ProfileImageVersion": 0,
              "DisplayName": "Jeff Farris",
              "DisplayNameLastFirst": "Farris, Jeff",
              "Username": "jeffmarkues",
              "LanguageDescription": "English (English)",
              "PronounsDescription": "He/Him"
            }
          ],
          "ID": 3261782,
          "Name": null,
          "StatusDescription": "Active",
          "IsActive": true
        },
        "ID": 10877800,
        "CheckedIn": null,
        "ResultConfirmed": "2025-06-20T00:32:48Z",
        "SortOrder": 1,
        "GameByes": 0,
        "GameWins": 2,
        "TeamId": 3261782,
        "GameWinsAndGameByes": 2,
        "Decklists": []
      }
    ],
    "ByeReason": null,
    "LossReason": null,
    "RoundName": null,
    "DateCreated": "2025-06-20T00:32:48Z",
    "Type": 0,
    "FeatureMatch": false,
    "HasResult": true,
    "TimeExtended": false,
    "MatchesPublished": true,
    "RoundNumber": 2,
    "GameDraws": 0,
    "PodNumber": null,
    "PhaseSortOrder": 1,
    "SortOrder": null,
    "TableNumber": 3,
    "TimeExtensionMinutes": null,
    "PhaseId": 328387,
    "RoundId": 1151673,
    "TournamentId": 328861,
    "FormatId": "920ec64f-a02f-4176-a3d0-0c46eef003cb",
    "Format": "Premodern",
    "Guid": "70008b45-b5ca-4c61-a50f-b30200009d3c",
    "TableLocation": null,
    "TableSection": null,
    "ByeReasonDescription": null,
    "LossReasonDescription": null,
    "ResultString": "Jeff Farris won 2-0-0",
    "RoundDescription": "Round 2",
    "TableNumberDescription": "3",
    "TypeDescription": "Best of Three",
    "FormatDescription": "Premodern",
    "AcknowledgedDecklists": false
  },
  {
    "Competitors": [
      {
        "Team": {
          "Players": [
            {
              "TeamId": 3261792,
              "ID": 3247128,
              "ScreenName": "N/A",
              "ProfileImageVersion": 0,
              "DisplayName": "sylvanisator",
              "DisplayNameLastFirst": "sylvanisator",
              "Username": "sylvanisator",
              "LanguageDescription": "Auto (English)",
              "PronounsDescription": null
            }
          ],
          "ID": 3261792,
          "Name": null,
          "StatusDescription": "Active",
          "IsActive": true
        },
        "ID": 10877801,
        "CheckedIn": null,
        "ResultConfirmed": "2025-06-20T00:50:16Z",
        "SortOrder": 0,
        "GameByes": null,
        "GameWins": null,
        "TeamId": 3261792,
        "GameWinsAndGameByes": 0,
        "Decklists": []
      },
      {
        "Team": {
          "Players": [
            {
              "TeamId": 3261813,
              "ID": 3247149,
              "ScreenName": "N/A",
              "ProfileImageVersion": 0,
              "DisplayName": "RichBucey",
              "DisplayNameLastFirst": "RichBucey",
              "Username": "RichBucey",
              "LanguageDescription": "Auto (English)",
              "PronounsDescription": null
            }
          ],
          "ID": 3261813,
          "Name": null,
          "StatusDescription": "Active",
          "IsActive": true
        },
        "ID": 10877802,
        "CheckedIn": null,
        "ResultConfirmed": "2025-06-20T00:38:22Z",
        "SortOrder": 1,
        "GameByes": 0,
        "GameWins": 2,
        "TeamId": 3261813,
        "GameWinsAndGameByes": 2,
        "Decklists": []
      }
    ],
    "ByeReason": null,
    "LossReason": null,
    "RoundName": null,
    "DateCreated": "2025-06-20T00:50:16Z",
    "Type": 0,
    "FeatureMatch": false,
    "HasResult": true,
    "TimeExtended": false,
    "MatchesPublished": true,
    "RoundNumber": 2,
    "GameDraws": 0,
    "PodNumber": null,
    "PhaseSortOrder": 1,
    "SortOrder": null,
    "TableNumber": 4,
    "TimeExtensionMinutes": null,
    "PhaseId": 328387,
    "RoundId": 1151673,
    "TournamentId": 328861,
    "FormatId": "920ec64f-a02f-4176-a3d0-0c46eef003cb",
    "Format": "Premodern",
    "Guid": "476394ca-6bcd-42d9-b48e-b30200009d40",
    "TableLocation": null,
    "TableSection": null,
    "ByeReasonDescription": null,
    "LossReasonDescription": null,
    "ResultString": "RichBucey won 2-0-0",
    "RoundDescription": "Round 2",
    "TableNumberDescription": "4",
    "TypeDescription": "Best of Three",
    "FormatDescription": "Premodern",
    "AcknowledgedDecklists": false
  },
  {
    "Competitors": [
      {
        "Team": {
          "Players": [
            {
              "TeamId": 3261784,
              "ID": 3247120,
              "ScreenName": "N/A",
              "ProfileImageVersion": 0,
              "DisplayName": "swb 👋",
              "DisplayNameLastFirst": "👋, swb",
              "Username": "swbmtg",
              "LanguageDescription": "Auto (English)",
              "PronounsDescription": "He/Him"
            }
          ],
          "ID": 3261784,
          "Name": null,
          "StatusDescription": "Active",
          "IsActive": true
        },
        "ID": 10877803,
        "CheckedIn": null,
        "ResultConfirmed": null,
        "SortOrder": 0,
        "GameByes": 0,
        "GameWins": 2,
        "TeamId": 3261784,
        "GameWinsAndGameByes": 2,
        "Decklists": []
      },
      {
        "Team": {
          "Players": [
            {
              "TeamId": 3261815,
              "ID": 3247151,
              "ScreenName": "N/A",
              "ProfileImageVersion": 3,
              "DisplayName": "Chris Cruz",
              "DisplayNameLastFirst": "Cruz, Chris",
              "Username": "JUDDERMANG",
              "LanguageDescription": "English (English)",
              "PronounsDescription": "He/They"
            }
          ],
          "ID": 3261815,
          "Name": null,
          "StatusDescription": "Active",
          "IsActive": true
        },
        "ID": 10877804,
        "CheckedIn": null,
        "ResultConfirmed": "2025-06-20T00:55:02Z",
        "SortOrder": 1,
        "GameByes": 0,
        "GameWins": 1,
        "TeamId": 3261815,
        "GameWinsAndGameByes": 1,
        "Decklists": []
      }
    ],
    "ByeReason": null,
    "LossReason": null,
    "RoundName": null,
    "DateCreated": "2025-06-20T00:55:02Z",
    "Type": 0,
    "FeatureMatch": false,
    "HasResult": true,
    "TimeExtended": false,
    "MatchesPublished": true,
    "RoundNumber": 2,
    "GameDraws": 0,
    "PodNumber": null,
    "PhaseSortOrder": 1,
    "SortOrder": null,
    "TableNumber": 5,
    "TimeExtensionMinutes": null,
    "PhaseId": 328387,
    "RoundId": 1151673,
    "TournamentId": 328861,
    "FormatId": "920ec64f-a02f-4176-a3d0-0c46eef003cb",
    "Format": "Premodern",
    "Guid": "b892c523-80ce-4788-8394-b30200009d4a",
    "TableLocation": null,
    "TableSection": null,
    "ByeReasonDescription": null,
    "LossReasonDescription": null,
    "ResultString": "swb 👋 won 2-1-0",
    "RoundDescription": "Round 2",
    "TableNumberDescription": "5",
    "TypeDescription": "Best of Three",
    "FormatDescription": "Premodern",
    "AcknowledgedDecklists": false
  }
]